requirements.txt
urls.json
cli/__init__.py
secretvalidate/.env
secretvalidate/__init__.py
secretvalidate/azure_storage_account_key_validator.py
secretvalidate/browserstack_validator.py
secretvalidate/entra_id_validator.py
secretvalidate/env_loader.py
secretvalidate/flickr_validator.py
secretvalidate/http_validator.py
secretvalidate/mongodb_validator.py
secretvalidate/new_relic_validator.py
secretvalidate/session_manager.py
secretvalidate/sonarcloud_validator.py
secretvalidate/teams_webhook_validator.py
secretvalidate/utility.py
secretvalidate/validator.py
secretvalidate-0.0.52.dist-info/licenses/LICENSE
secretvalidate-0.0.52.dist-info/METADATA
secretvalidate-0.0.52.dist-info/WHEEL
secretvalidate-0.0.52.dist-info/entry_points.txt
secretvalidate-0.0.52.dist-info/top_level.txt
secretvalidate-0.0.52.dist-info/RECORD
