Metadata-Version: 2.4
Name: secretvalidate
Version: 0.0.52
Summary: A cli/package for validating secrets.
Author: VigneshKna
Author-email: Vkna@email.com
License: MIT
License-File: LICENSE
Requires-Dist: click
Requires-Dist: requests
Requires-Dist: setuptools
Requires-Dist: twine
Requires-Dist: pyOpenSSL
Requires-Dist: wheel
Requires-Dist: pymongo
Requires-Dist: python-dotenv
Requires-Dist: azure-storage-blob
Requires-Dist: pyjwt
Dynamic: author
Dynamic: author-email
Dynamic: license
Dynamic: license-file
Dynamic: requires-dist
Dynamic: summary
